ansible_galaxy_local_deps/__init__.py
ansible_galaxy_local_deps/changedep.py
ansible_galaxy_local_deps/deps.py
ansible_galaxy_local_deps/dump.py
ansible_galaxy_local_deps/finder.py
ansible_galaxy_local_deps/gengithubactions.py
ansible_galaxy_local_deps/installdeps.py
ansible_galaxy_local_deps/logging_setup.py
ansible_galaxy_local_deps/platform_matrix.py
ansible_galaxy_local_deps/py.typed
ansible_galaxy_local_deps/slurp.py
ansible_galaxy_local_deps/writedeps.py
ansible_galaxy_local_deps-0.6.0.dist-info/METADATA
ansible_galaxy_local_deps-0.6.0.dist-info/WHEEL
ansible_galaxy_local_deps-0.6.0.dist-info/entry_points.txt
ansible_galaxy_local_deps-0.6.0.dist-info/licenses/LICENSE
ansible_galaxy_local_deps-0.6.0.dist-info/RECORD
