Metadata-Version: 2.4
Name: ansible-galaxy-local-deps
Version: 0.6.0
Summary: CLI for interacting with Ansible roles and their CIs
Author-email: Andrew Rothstein <andrew.rothstein@gmail.com>
License-File: LICENSE
Requires-Python: >=3.12
Requires-Dist: pyyaml
